{"cameraMode":{"drawMode":0,"name":"Shaded","section":"Shading Mode"},"sceneLighting":false,"audioPlay":false,"sceneViewState":{"m_AlwaysRefresh":false,"showFog":true,"showSkybox":false,"showFlares":true,"showImageEffects":true,"showParticleSystems":true,"showVisualEffectGraphs":true,"m_FxEnabled":true},"in2DMode":false,"pivot":{"x":2.26920485496521,"y":0.5158731937408447,"z":-0.04962668940424919},"rotation":{"x":0.03779903054237366,"y":-0.008998202160000801,"z":0.00034035544376820326,"w":0.9992455840110779},"size":3.816084384918213,"orthographic":false}